old_pdftoppm_windows_local/__init__.py
old_pdftoppm_windows_local/xpdf_tools_win_4_01_01/__init__.py
old_pdftoppm_windows_local/xpdf_tools_win_4_01_01/bin32/__init__.py
old_pdftoppm_windows_local/xpdf_tools_win_4_01_01/bin64/__init__.py
pdfCropMargins/__init__.py
pdfCropMargins/__main__.py
pdfCropMargins/calculate_bounding_boxes.py
pdfCropMargins/directory_locator.py
pdfCropMargins/external_program_calls.py
pdfCropMargins/get_window_sizing_info.py
pdfCropMargins/gui.py
pdfCropMargins/main_pdfCropMargins.py
pdfCropMargins/manpage_data.py
pdfCropMargins/pdfCropMargins.py
pdfCropMargins/prettified_argparse.py
pdfCropMargins/pymupdf_routines.py
pdfCropMargins/vendor/__init__.py
pdfCropMargins/vendor/pysimplegui_4_foss/PySimpleGUI.py
pdfCropMargins/vendor/pysimplegui_4_foss/__init__.py
pdfcropmargins-2.2.1.dist-info/licenses/LICENSE
pdfcropmargins-2.2.1.dist-info/METADATA
pdfcropmargins-2.2.1.dist-info/WHEEL
pdfcropmargins-2.2.1.dist-info/entry_points.txt
pdfcropmargins-2.2.1.dist-info/top_level.txt
pdfcropmargins-2.2.1.dist-info/RECORD
