Metadata-Version: 2.4
Name: pdfCropMargins
Version: 2.2.1
Summary: A command-line program to crop the margins of PDF files, with many options.
Author-email: Allen Barker <Allen.L.Barker@gmail.com>
License: 
Project-URL: Homepage, https://github.com/abarker/pdfCropMargins
Keywords: crop,margins,pdf,resize
Classifier: Development Status :: 5 - Production/Stable
Classifier: Intended Audience :: End Users/Desktop
Classifier: License :: OSI Approved :: GNU General Public License (GPL)
Classifier: Operating System :: Microsoft :: Windows
Classifier: Operating System :: POSIX
Classifier: Operating System :: Unix
Classifier: Programming Language :: Python
Classifier: Programming Language :: Python :: 3
Classifier: Programming Language :: Python :: 3.7
Classifier: Programming Language :: Python :: 3.8
Classifier: Programming Language :: Python :: 3.9
Classifier: Programming Language :: Python :: Implementation :: CPython
Classifier: Programming Language :: Python :: Implementation :: PyPy
Classifier: Programming Language :: Python :: 3.10
Classifier: Topic :: Utilities
License-File: LICENSE
Requires-Dist: pillow>=10.1.0
Requires-Dist: PyMuPDF>=1.19.6
Requires-Dist: wheel
Dynamic: license-file
